cloudevents/__init__.py
cloudevents/conversion.py
cloudevents/exceptions.py
cloudevents/py.typed
cloudevents/abstract/__init__.py
cloudevents/abstract/event.py
cloudevents/http/__init__.py
cloudevents/http/conversion.py
cloudevents/http/event.py
cloudevents/http/event_type.py
cloudevents/http/http_methods.py
cloudevents/http/json_methods.py
cloudevents/http/util.py
cloudevents/kafka/__init__.py
cloudevents/kafka/conversion.py
cloudevents/kafka/exceptions.py
cloudevents/pydantic/__init__.py
cloudevents/pydantic/fields_docs.py
cloudevents/pydantic/v1/__init__.py
cloudevents/pydantic/v1/conversion.py
cloudevents/pydantic/v1/event.py
cloudevents/pydantic/v2/__init__.py
cloudevents/pydantic/v2/conversion.py
cloudevents/pydantic/v2/event.py
cloudevents/sdk/__init__.py
cloudevents/sdk/exceptions.py
cloudevents/sdk/marshaller.py
cloudevents/sdk/types.py
cloudevents/sdk/converters/__init__.py
cloudevents/sdk/converters/base.py
cloudevents/sdk/converters/binary.py
cloudevents/sdk/converters/structured.py
cloudevents/sdk/converters/util.py
cloudevents/sdk/event/__init__.py
cloudevents/sdk/event/attribute.py
cloudevents/sdk/event/base.py
cloudevents/sdk/event/opt.py
cloudevents/sdk/event/v03.py
cloudevents/sdk/event/v1.py
cloudevents-1.10.1.dist-info/LICENSE
cloudevents-1.10.1.dist-info/METADATA
cloudevents-1.10.1.dist-info/WHEEL
cloudevents-1.10.1.dist-info/top_level.txt
cloudevents-1.10.1.dist-info/zip-safe
cloudevents-1.10.1.dist-info/RECORD
