Metadata-Version: 2.1
Name: cloudevents
Version: 1.10.1
Summary: CloudEvents Python SDK
Home-page: https://github.com/cloudevents/sdk-python
Author: The Cloud Events Contributors
Author-email: cncfcloudevents@gmail.com
License: https://www.apache.org/licenses/LICENSE-2.0
Keywords: CloudEvents Eventing Serverless
Classifier: Intended Audience :: Information Technology
Classifier: Intended Audience :: System Administrators
Classifier: Intended Audience :: Developers
Classifier: License :: OSI Approved :: Apache Software License
Classifier: Development Status :: 5 - Production/Stable
Classifier: Operating System :: OS Independent
Classifier: Natural Language :: English
Classifier: Programming Language :: Python
Classifier: Programming Language :: Python :: 3
Classifier: Programming Language :: Python :: 3 :: Only
Classifier: Programming Language :: Python :: 3.7
Classifier: Programming Language :: Python :: 3.8
Classifier: Programming Language :: Python :: 3.9
Classifier: Programming Language :: Python :: 3.10
Classifier: Programming Language :: Python :: 3.11
Classifier: Typing :: Typed
License-File: LICENSE
Requires-Dist: deprecation<3.0,>=2.0
Provides-Extra: pydantic
Requires-Dist: pydantic<3.0,>=1.0.0; extra == "pydantic"
